{
  "date": "Mar 5th, 1980",
  "gallery-id": "72157714213122193",
  "nps-url": "https://www.nps.gov/chis/index.htm",
  "description": "Channel Islands National Park encompasses five remarkable islands and their ocean environment, preserving and protecting a wealth of natural and cultural resources. Isolation over thousands of years has created unique animals, plants, and archeological resources found nowhere else on Earth and helped preserve a place where visitors can experience coastal southern California as it once was.",
  "title": "Channel Islands National Park",
  "location": "Santa Barbara & Ventura Counties, CA"
}